setup.py
bTn/__init__.py
bTn/colors.py
pygame_buttons.egg-info/PKG-INFO
pygame_buttons.egg-info/SOURCES.txt
pygame_buttons.egg-info/dependency_links.txt
pygame_buttons.egg-info/requires.txt
pygame_buttons.egg-info/top_level.txt