Metadata-Version: 1.0
Name: pygame-buttons
Version: 0.1.32
Summary: pygame按钮控件
Home-page: https://code.xueersi.com
Author: Ruoyu Wang
Author-email: UNKNOWN
License: UNKNOWN
Platform: UNKNOWN
